email_inspector/__init__.py
email_inspector/free_providers.py
email_inspector/data/free_providers.json
email_inspector-0.1.4.dist-info/METADATA
email_inspector-0.1.4.dist-info/WHEEL
email_inspector-0.1.4.dist-info/top_level.txt
email_inspector-0.1.4.dist-info/RECORD
