Metadata-Version: 2.4
Name: email-inspector
Version: 0.1.4
Summary: Detect free/public email provider domains (gmail, yahoo, outlook, ...)
Author-email: Jahanvi Raycha <raychajahanvi@gmail.com>
License: MIT
Requires-Python: >=3.8
Requires-Dist: dnspython>=2.0.0; extra == "mx"
Provides-Extra: test
Requires-Dist: pytest>=7.0.0; extra == "test"
